accessibility/__init__.py
accessibility/admin.py
accessibility/apps.py
accessibility/context_processors.py
accessibility/forms.py
accessibility/models.py
accessibility/tests.py
accessibility/urls.py
accessibility/views.py
accessibility/migrations/0001_initial.py
accessibility/migrations/0002_alter_allinoneaccessibility_aioa_icon_size_and_more.py
accessibility/migrations/__init__.py
accessibility/static/admin/css/aioa_admin.css
accessibility/static/admin/js/aioa_accessibility.js
accessibility/static/admin/js/aioa_icon_sync.js
accessibility/templates/home.html
mezzanine_all_in_one_accessibility/__init__.py
mezzanine_all_in_one_accessibility/local_settings.py
mezzanine_all_in_one_accessibility/settings.py
mezzanine_all_in_one_accessibility/urls.py
mezzanine_all_in_one_accessibility/wsgi.py
mezzanine_all_in_one_accessibility-1.0.1.dist-info/METADATA
mezzanine_all_in_one_accessibility-1.0.1.dist-info/WHEEL
mezzanine_all_in_one_accessibility-1.0.1.dist-info/top_level.txt
mezzanine_all_in_one_accessibility-1.0.1.dist-info/RECORD
