Metadata-Version: 2.4
Name: mezzanine-all-in-one-accessibility
Version: 1.0.1
Summary: Website accessibility widget for improving WCAG 2.0, 2.1, 2.2 and ADA compliance!
Home-page: https://www.skynettechnologies.com
Author: Skynet Technologies USA LLC
Author-email: developer3@skynettechnologies.com
Classifier: Environment :: Web Environment
Classifier: Framework :: Django
Classifier: Framework :: Django :: 4.2
Classifier: Intended Audience :: Developers
Classifier: License :: OSI Approved :: BSD License
Classifier: Operating System :: OS Independent
Classifier: Programming Language :: Python
Classifier: Programming Language :: Python :: 3.11
Classifier: Topic :: Internet :: WWW/HTTP
Classifier: Topic :: Internet :: WWW/HTTP :: Dynamic Content
Requires-Dist: Django==4.2
Requires-Dist: Mezzanine<=6.1.1,>=5.1.0
Dynamic: description-content-type
